kamla_cli/__init__.py
kamla_cli/cli.py
kamla_cli/inhouse_api.py
kamla_cli/utils.py
kamla_cli-0.1.1.dist-info/LICENSE
kamla_cli-0.1.1.dist-info/METADATA
kamla_cli-0.1.1.dist-info/WHEEL
kamla_cli-0.1.1.dist-info/entry_points.txt
kamla_cli-0.1.1.dist-info/top_level.txt
kamla_cli-0.1.1.dist-info/RECORD
