Metadata-Version: 2.1
Name: kamla-cli
Version: 0.1.1
Summary: Inhouse Ten CLI
Home-page: https://github.com/nurtasin/kamla-cli
Author: NurTasin
Author-email: nmuatasin2005@gmail.com
Classifier: Programming Language :: Python :: 3
Classifier: License :: OSI Approved :: MIT License
Classifier: Operating System :: OS Independent
Requires-Python: >=3.6
License-File: LICENSE
Requires-Dist: pwinput >=1.0.0
Requires-Dist: texttable >=1.6.3
Requires-Dist: pytz >=2021.3
Requires-Dist: requests >=2.26.0
